{
  "id": "shg_101_do_you_like_money",
  "title": "Do You Like Money?",
  "angle": "money_hook",
  "duration_sec": 12,
  "voiceover": "Do you like money? Then you need to see this. The Side Hustle Guild pays real cash every month. The contest pool is funded by the community itself. Twenty-five percent of every subscription. Come check us out. Link is in the bio.",
  "captions": [
    {
      "start": 0.0,
      "end": 1.8,
      "text": "DO YOU LIKE MONEY?"
    },
    {
      "start": 1.8,
      "end": 4.0,
      "text": "You need to see this."
    },
    {
      "start": 4.0,
      "end": 6.2,
      "text": "The Side Hustle Guild"
    },
    {
      "start": 6.2,
      "end": 8.5,
      "text": "Real cash. Every month."
    },
    {
      "start": 8.5,
      "end": 10.0,
      "text": "Funded by the community."
    },
    {
      "start": 10.0,
      "end": 12.0,
      "text": "Come check us out. Link is in the bio."
    }
  ],
  "scenes": [
    {
      "start": 0.0,
      "end": 1.8,
      "broll_topic": "stack_of_cash_close_up"
    },
    {
      "start": 1.8,
      "end": 3.0,
      "broll_topic": "person_at_laptop_smiling"
    },
    {
      "start": 3.0,
      "end": 4.0,
      "broll_topic": "phone_notification_payment"
    },
    {
      "start": 4.0,
      "end": 5.5,
      "broll_topic": "discord_community_screen"
    },
    {
      "start": 5.5,
      "end": 7.0,
      "broll_topic": "homepage_hero_branded"
    },
    {
      "start": 7.0,
      "end": 8.0,
      "broll_topic": "cash_prize_winning_moment"
    },
    {
      "start": 8.0,
      "end": 9.0,
      "broll_topic": "calendar_calendar_calendar"
    },
    {
      "start": 9.0,
      "end": 9.7,
      "broll_topic": "calculator_math_percent"
    },
    {
      "start": 9.7,
      "end": 10.3,
      "broll_topic": "subscription_billing_screen"
    },
    {
      "start": 10.3,
      "end": 11.0,
      "broll_topic": "phone_bio_link_tap"
    },
    {
      "start": 11.0,
      "end": 11.6,
      "broll_topic": "shg_brand_endcard"
    },
    {
      "start": 11.6,
      "end": 12.0,
      "broll_topic": "shg_brand_endcard"
    }
  ],
  "cta_url": "https://thesidehustleguild.com/",
  "post_caption": "Real cash, every month. Funded by the community. The Side Hustle Guild.",
  "hashtags": [
    "#sidehustle",
    "#cashprize",
    "#community",
    "#discordcommunity"
  ],
  "brand_id": "thesidehustleguild",
  "aspect_ratio": {
    "width": 1080,
    "height": 1920
  },
  "platforms": [
    "tiktok",
    "reels",
    "shorts"
  ],
  "compliance": {
    "earnings_disclaimer": "Member results not typical. Educational community."
  }
}